calculadora/__init__.py
calculadora/calculadora.py
tests/__init__.py
tests/test_calculadora.py
calculadora8-0.2.0.dist-info/LICENSE
calculadora8-0.2.0.dist-info/METADATA
calculadora8-0.2.0.dist-info/WHEEL
calculadora8-0.2.0.dist-info/top_level.txt
calculadora8-0.2.0.dist-info/RECORD
